[
  {
    "outputFileName": "wwwroot/css/site.min.css",
    "inputFiles": ["wwwroot/css/site.css"]
  },
  {
    "outputFileName": "wwwroot/js/site.min.js",
    "inputFiles": [
      "wwwroot/js/details.polyfill.js",
      "wwwroot/js/shim-links-with-button-role.js",
      "wwwroot/js/show-hide-content.js",
      "wwwroot/js/site-nav.js",
      "wwwroot/js/site.js",
      "wwwroot/js/cookiebanner.js"
    ],
    "minify": {
      "renameLocals": true
    }
  },
  {
    "outputFileName": "wwwroot/js/site-validation.min.js",
    "inputFiles": ["wwwroot/js/site-validation.js"],
    "minify": {
      "renameLocals": true
    }
  }
]
